omicspreprocessing/__init__.py
omicspreprocessing/core.py
omicspreprocessing/parallel_computing.py
omicspreprocessing-0.1.2.dist-info/licenses/LICENSE
omicspreprocessing-0.1.2.dist-info/METADATA
omicspreprocessing-0.1.2.dist-info/WHEEL
omicspreprocessing-0.1.2.dist-info/top_level.txt
omicspreprocessing-0.1.2.dist-info/RECORD
